[
    {
        "N_samples": 100,
        "N_trees": 20,
        "epsilon": 20,
        "epsilon_etape": 1.0,
        "obj_active": 1,
        "reconstruction_error": 0.09571428571428568,
        "all_distances": [
            0.0,
            0.07142857142857142,
            0.07142857142857142,
            0.0,
            0.07142857142857142,
            0.0,
            0.0,
            0.0,
            0.0,
            0.07142857142857142,
            0.0,
            0.21428571428571427,
            0.0,
            0.0,
            0.0,
            0.07142857142857142,
            0.0,
            0.07142857142857142,
            0.0,
            0.21428571428571427,
            0.21428571428571427,
            0.14285714285714285,
            0.14285714285714285,
            0.21428571428571427,
            0.14285714285714285,
            0.2857142857142857,
            0.0,
            0.0,
            0.0,
            0.0,
            0.14285714285714285,
            0.0,
            0.14285714285714285,
            0.14285714285714285,
            0.0,
            0.0,
            0.0,
            0.0,
            0.07142857142857142,
            0.21428571428571427,
            0.0,
            0.14285714285714285,
            0.14285714285714285,
            0.07142857142857142,
            0.0,
            0.0,
            0.07142857142857142,
            0.0,
            0.0,
            0.14285714285714285,
            0.07142857142857142,
            0.0,
            0.14285714285714285,
            0.0,
            0.0,
            0.07142857142857142,
            0.0,
            0.07142857142857142,
            0.14285714285714285,
            0.0,
            0.0,
            0.21428571428571427,
            0.0,
            0.0,
            0.0,
            0.0,
            0.0,
            0.0,
            0.0,
            0.0,
            0.07142857142857142,
            0.0,
            0.2857142857142857,
            0.2857142857142857,
            0.2857142857142857,
            0.2857142857142857,
            0.21428571428571427,
            0.14285714285714285,
            0.2857142857142857,
            0.2857142857142857,
            0.2857142857142857,
            0.2857142857142857,
            0.21428571428571427,
            0.42857142857142855,
            0.35714285714285715,
            0.2857142857142857,
            0.42857142857142855,
            0.14285714285714285,
            0.2857142857142857,
            0.07142857142857142,
            0.0,
            0.07142857142857142,
            0.21428571428571427,
            0.0,
            0.21428571428571427,
            0.0,
            0.07142857142857142,
            0.0,
            0.0,
            0.07142857142857142
        ],
        "all_distances_x_train_ids": [
            25,
            87,
            11,
            56,
            49,
            84,
            31,
            53,
            90,
            12,
            93,
            58,
            45,
            22,
            94,
            17,
            68,
            10,
            37,
            20,
            78,
            89,
            3,
            23,
            69,
            83,
            21,
            6,
            32,
            99,
            38,
            42,
            46,
            67,
            2,
            8,
            96,
            74,
            28,
            52,
            59,
            73,
            43,
            30,
            14,
            41,
            26,
            36,
            9,
            51,
            55,
            44,
            86,
            81,
            29,
            50,
            40,
            33,
            13,
            57,
            76,
            98,
            82,
            35,
            39,
            63,
            85,
            27,
            92,
            34,
            4,
            61,
            65,
            60,
            5,
            54,
            19,
            64,
            91,
            75,
            72,
            7,
            47,
            62,
            66,
            79,
            88,
            15,
            95,
            16,
            48,
            1,
            24,
            77,
            70,
            80,
            18,
            0,
            71,
            97
        ],
        "duration": 7203.670511484146,
        "solver_status": "FEASIBLE",
        "N_reconstruit": 91,
        "accuracy_train": 0.7,
        "accuracy_test": 0.6322825781030116,
        "dataset": "data/compas.csv",
        "time_out": 7200,
        "check_ohe": true,
        "succes_total_debruitage": false,
        "seed": 1,
        "depth": 3,
        "id": 196
    }
]