[
    {
        "N_samples": 100,
        "N_trees": 10,
        "epsilon": 5,
        "epsilon_etape": 0.5,
        "obj_active": 1,
        "reconstruction_error": 0.17642857142857127,
        "all_distances": [
            0.0,
            0.0,
            0.0,
            0.0,
            0.14285714285714285,
            0.07142857142857142,
            0.14285714285714285,
            0.07142857142857142,
            0.0,
            0.07142857142857142,
            0.0,
            0.14285714285714285,
            0.0,
            0.42857142857142855,
            0.2857142857142857,
            0.07142857142857142,
            0.14285714285714285,
            0.2857142857142857,
            0.2857142857142857,
            0.2857142857142857,
            0.2857142857142857,
            0.2857142857142857,
            0.14285714285714285,
            0.2857142857142857,
            0.21428571428571427,
            0.14285714285714285,
            0.14285714285714285,
            0.2857142857142857,
            0.5,
            0.2857142857142857,
            0.2857142857142857,
            0.07142857142857142,
            0.2857142857142857,
            0.21428571428571427,
            0.35714285714285715,
            0.35714285714285715,
            0.14285714285714285,
            0.2857142857142857,
            0.2857142857142857,
            0.2857142857142857,
            0.14285714285714285,
            0.21428571428571427,
            0.42857142857142855,
            0.21428571428571427,
            0.42857142857142855,
            0.21428571428571427,
            0.2857142857142857,
            0.42857142857142855,
            0.42857142857142855,
            0.42857142857142855,
            0.21428571428571427,
            0.21428571428571427,
            0.35714285714285715,
            0.14285714285714285,
            0.14285714285714285,
            0.0,
            0.0,
            0.0,
            0.07142857142857142,
            0.0,
            0.07142857142857142,
            0.35714285714285715,
            0.14285714285714285,
            0.0,
            0.21428571428571427,
            0.07142857142857142,
            0.14285714285714285,
            0.2857142857142857,
            0.07142857142857142,
            0.0,
            0.07142857142857142,
            0.14285714285714285,
            0.21428571428571427,
            0.21428571428571427,
            0.21428571428571427,
            0.14285714285714285,
            0.21428571428571427,
            0.07142857142857142,
            0.07142857142857142,
            0.21428571428571427,
            0.0,
            0.07142857142857142,
            0.14285714285714285,
            0.14285714285714285,
            0.14285714285714285,
            0.0,
            0.07142857142857142,
            0.21428571428571427,
            0.14285714285714285,
            0.07142857142857142,
            0.14285714285714285,
            0.0,
            0.14285714285714285,
            0.21428571428571427,
            0.07142857142857142,
            0.42857142857142855,
            0.21428571428571427,
            0.2857142857142857,
            0.0,
            0.2857142857142857
        ],
        "all_distances_x_train_ids": [
            56,
            25,
            15,
            20,
            58,
            12,
            35,
            32,
            17,
            90,
            60,
            46,
            84,
            82,
            38,
            50,
            16,
            57,
            41,
            37,
            85,
            19,
            98,
            11,
            64,
            65,
            59,
            26,
            13,
            30,
            91,
            62,
            72,
            48,
            73,
            18,
            47,
            9,
            23,
            55,
            24,
            77,
            88,
            34,
            94,
            3,
            95,
            66,
            51,
            7,
            74,
            4,
            76,
            81,
            14,
            31,
            49,
            29,
            6,
            44,
            93,
            69,
            70,
            63,
            92,
            33,
            42,
            67,
            54,
            28,
            53,
            22,
            43,
            21,
            27,
            36,
            39,
            1,
            61,
            86,
            45,
            78,
            10,
            2,
            5,
            96,
            87,
            71,
            0,
            40,
            8,
            79,
            75,
            52,
            68,
            89,
            99,
            80,
            83,
            97
        ],
        "duration": 7212.311035871506,
        "solver_status": "FEASIBLE",
        "N_reconstruit": 92,
        "accuracy_train": 0.68,
        "accuracy_test": 0.6400225161835069,
        "dataset": "data/compas.csv",
        "time_out": 7200,
        "check_ohe": true,
        "succes_total_debruitage": false,
        "seed": 1,
        "depth": 5,
        "id": 496
    }
]